{
  "listData": [
    {
      "title": "Deep earth",
      "img": "./images/desktop/image-deep-earth.jpg",
      "mImg": "./images/mobile/image-deep-earth.jpg"
    },
    {
      "title": "Night arcade",
      "img": "./images/desktop/image-night-arcade.jpg",
      "mImg": "./images/mobile/image-night-arcade.jpg"
    },
    {
      "title": "Soccer team VR",
      "img": "./images/desktop/image-soccer-team.jpg",
      "mImg": "./images/mobile/image-soccer-team.jpg"
    },
    {
      "title": "The grid",
      "img": "./images/desktop/image-grid.jpg",
      "mImg": "./images/mobile/image-grid.jpg"
    },
    {
      "title": "From up above VR",
      "img": "./images/desktop/image-from-above.jpg",
      "mImg": "./images/mobile/image-from-above.jpg"
    },
    {
      "title": "Pocket borealis",
      "img": "./images/desktop/image-pocket-borealis.jpg",
      "mImg": "./images/mobile/image-pocket-borealis.jpg"
    },
    {
      "title": "The curiosity",
      "img": "./images/desktop/image-curiosity.jpg",
      "mImg": "./images/mobile/image-curiosity.jpg"
    },
    {
      "title": "Make it fisheye",
      "img": "./images/desktop/image-fisheye.jpg",
      "mImg": "./images/mobile/image-fisheye.jpg"
    }
  ]
}
